.gitignore
LICENSE.txt
MANIFEST.in
README.rst
setup.py
bitstream.egg-info/PKG-INFO
bitstream.egg-info/SOURCES.txt
bitstream.egg-info/dependency_links.txt
bitstream.egg-info/not-zip-safe
bitstream.egg-info/pbr.json
bitstream.egg-info/top_level.txt
src/bitstream.c
src/bitstream.pxd
src/bitstream.pyx